{
    "code": 3308,
    "parent": 33,
    "name": "MAGELANG",
    "latitude": "-7.5135657684998",
    "longitude": "110.2447700535",
    "postal": [
        56500,
        56100
    ],
    "children": [
        3308010,
        3308020,
        3308030,
        3308040,
        3308050,
        3308060,
        3308070,
        3308080,
        3308090,
        3308100,
        3308110,
        3308120,
        3308130,
        3308140,
        3308150,
        3308160,
        3308170,
        3308180,
        3308190,
        3308200,
        3308210
    ]
}