{
    "code": 1275,
    "parent": 12,
    "name": "MEDAN",
    "latitude": "3.6423669029996",
    "longitude": "98.669493706988",
    "postal": [
        20100,
        20200,
        20400,
        20500
    ],
    "children": [
        1275010,
        1275020,
        1275030,
        1275040,
        1275050,
        1275060,
        1275070,
        1275080,
        1275090,
        1275100,
        1275110,
        1275120,
        1275130,
        1275140,
        1275150,
        1275160,
        1275170,
        1275180,
        1275190,
        1275200,
        1275210
    ]
}